[
    {
        "name": "Trident IV",
        "image": "images/trident_iv.png",
        "dataFile": "data/trident_iv.json"
    },
    {
        "name": "Trident V",
        "image": "images/trident_v.png",
        "dataFile": "data/trident_v.json"
    },
    {
        "name": "Trident VI",
        "image": "images/trident_vi.png",
        "dataFile": "data/trident_vi.json"
    },
    {
        "name": "Trident VII",
        "image": "images/trident_vii.png",
        "dataFile": "data/trident_vii.json"
    },
    {
        "name": "Trident IX",
        "image": "images/trident_ix.png",
        "dataFile": "data/trident_ix.json"
    },
    {
        "name": "Trident: Test Realm",
        "image": "images/trident_tr.png",
        "dataFile": "data/trident_tr.json"
    },
    {
        "name": "Trident: Hardcore",
        "image": "images/trident_hardcore.png",
        "dataFile": "data/trident_hardcore_iii.json"
    },
    {
        "name": "Trident: Terraria",
        "image": "images/trident_terraria.png",
        "dataFile": "data/trident_terraria.json"
    }
]